cryptodock/__init__.py
cryptodock/__main__.py
cryptodock/sdk.py
cryptodock/api/__init__.py
cryptodock/api/api.py
cryptodock/api/controllers/__init__.py
cryptodock/api/controllers/coinbasepro.py
cryptodock/api/controllers/kucoin.py
cryptodock/api/controllers/local.py
cryptodock/backtest/__init__.py
cryptodock/backtest/backtest.py
cryptodock/strategy/__init__.py
cryptodock/strategy/config.py
cryptodock/strategy/strategy.py
cryptodock_sdk-0.1.3.dist-info/LICENCE.md
cryptodock_sdk-0.1.3.dist-info/METADATA
cryptodock_sdk-0.1.3.dist-info/WHEEL
cryptodock_sdk-0.1.3.dist-info/top_level.txt
cryptodock_sdk-0.1.3.dist-info/RECORD
