Metadata-Version: 2.1
Name: cryptodock-sdk
Version: 0.1.3
Summary: SDK for CryptoDock's remote API. Includes an semantic API interface, Strategy Wrapper and Backtest Wrapper. The SDK is meant to be leveraged with strategies bootstrapped from the CryptoDock desktop interface. Strategy trading and backtesting is managed through the desktop app interface.
Home-page: https://github.com/the-launch-tech/cryptodock-sdk
Author: Daniel Griffiths
Author-email: daniel@thelaunch.tech
License: MIT
Platform: UNKNOWN
Classifier: License :: OSI Approved :: MIT License
Classifier: Programming Language :: Python :: 3.7
Requires-Dist: requests
